setup.py
meshtool/__init__.py
meshtool/__main__.py
meshtool/util.py
meshtool.egg-info/PKG-INFO
meshtool.egg-info/SOURCES.txt
meshtool.egg-info/dependency_links.txt
meshtool.egg-info/entry_points.txt
meshtool.egg-info/top_level.txt
meshtool/args/__init__.py
meshtool/filters/__init__.py
meshtool/filters/base_filters.py
meshtool/filters/atlas_filters/__init__.py
meshtool/filters/atlas_filters/make_atlases.py
meshtool/filters/atlas_filters/rectpack.py
meshtool/filters/load_filters/__init__.py
meshtool/filters/load_filters/load_collada.py
meshtool/filters/load_filters/load_obj.py
meshtool/filters/meta_filters/__init__.py
meshtool/filters/meta_filters/full_optimizations.py
meshtool/filters/meta_filters/medium_optimizations.py
meshtool/filters/optimize_filters/__init__.py
meshtool/filters/optimize_filters/adjust_texcoords.py
meshtool/filters/optimize_filters/combine_effects.py
meshtool/filters/optimize_filters/combine_materials.py
meshtool/filters/optimize_filters/combine_primitives.py
meshtool/filters/optimize_filters/generate_normals.py
meshtool/filters/optimize_filters/normalize_indices.py
meshtool/filters/optimize_filters/optimize_sources.py
meshtool/filters/optimize_filters/optimize_textures.py
meshtool/filters/optimize_filters/save_mipmaps.py
meshtool/filters/optimize_filters/split_triangle_texcoords.py
meshtool/filters/optimize_filters/strip_empty_geometry.py
meshtool/filters/optimize_filters/strip_lines.py
meshtool/filters/optimize_filters/strip_unused_sources.py
meshtool/filters/optimize_filters/triangulate.py
meshtool/filters/panda_filters/__init__.py
meshtool/filters/panda_filters/collada_viewer.py
meshtool/filters/panda_filters/pandacontrols.py
meshtool/filters/panda_filters/pandacore.py
meshtool/filters/panda_filters/pm_viewer.py
meshtool/filters/panda_filters/save_rotate_screenshots.py
meshtool/filters/panda_filters/save_screenshot.py
meshtool/filters/panda_filters/viewer.py
meshtool/filters/panda_filters/pdae_utils/__init__.py
meshtool/filters/panda_filters/pdae_utils/pdae_python.py
meshtool/filters/panda_filters/pdae_utils/setup.py
meshtool/filters/print_filters/__init__.py
