Metadata-Version: 1.0
Name: meshtool
Version: 0.3
Summary: Tool for manipulating collada meshes
Home-page: https://github.com/pycollada/meshtool
Author: Jeff Terrace and contributors
Author-email: jterrace@gmail.com
License: BSD
Platform: any
